MANIFEST.in
README
setup.py
change_email/__init__.py
change_email/admin.py
change_email/conf.py
change_email/forms.py
change_email/managers.py
change_email/models.py
change_email/signals.py
change_email/urls.py
change_email/validators.py
change_email/views.py
change_email/fixtures/django_change_email_test_forms_fixtures.json
change_email/fixtures/django_change_email_test_models_fixtures.json
change_email/fixtures/django_change_email_test_views_fixtures.json
change_email/locale/de/LC_MESSAGES/django.mo
change_email/locale/de/LC_MESSAGES/django.po
change_email/locale/en/LC_MESSAGES/django.mo
change_email/locale/en/LC_MESSAGES/django.po
change_email/locale/fr/LC_MESSAGES/django.mo
change_email/locale/fr/LC_MESSAGES/django.po
change_email/management/__init__.py
change_email/management/commands/__init__.py
change_email/management/commands/cleanupemailchangerequests.py
change_email/tests/__init__.py
change_email/tests/forms.py
change_email/tests/lib.py
change_email/tests/models.py
change_email/tests/settings.py
change_email/tests/urls.py
change_email/tests/views.py
change_email/tests/templates/change_email/emailchange_confirm.html
change_email/tests/templates/change_email/emailchange_confirm_delete.html
change_email/tests/templates/change_email/emailchange_detail.html
change_email/tests/templates/change_email/emailchange_done.html
change_email/tests/templates/change_email/emailchange_form.html
change_email/tests/templates/change_email/mail/body.html
change_email/tests/templates/change_email/mail/body.txt
change_email/tests/templates/change_email/mail/subject.txt
django_change_email.egg-info/PKG-INFO
django_change_email.egg-info/SOURCES.txt
django_change_email.egg-info/dependency_links.txt
django_change_email.egg-info/not-zip-safe
django_change_email.egg-info/requires.txt
django_change_email.egg-info/top_level.txt