Metadata-Version: 1.1
Name: django-change-email
Version: 0.1.3
Summary: A Django application to enable users to change their e-mail address.
Home-page: https://github.com/tarak/django-change-email
Author: Tarak Blah
Author-email: halbkarat@gmail.com
License: UNKNOWN
Platform: UNKNOWN
Classifier: Development Status :: 4 - Beta
Classifier: Environment :: Web Environment
Classifier: Intended Audience :: Developers
Classifier: Operating System :: OS Independent
Classifier: Programming Language :: Python
Classifier: Framework :: Django
